{
    "0" : "Rean",
    "1" : "Alisa",
    "2" : "Elliot",
    "3" : "Laura",
    "4" : "Machias",
    "5" : "Emma",
    "6" : "Jusis",
    "7" : "Fie",
    "8" : "Gaius",
    "9" : "Millium",
    "10" : "Juna",
    "11" : "Kurt",
    "12" : "Altina",
    "13" : "Musse",
    "14" : "Ash",
    "15" : "Sara",
    "16" : "Aurelia",
    "17" : "Agate",
    "18" : "Angelica",
    "19" : "Olivert",
    "20" : "Tita",
    "21" : "Tio",
    "22" : "Sharon",
    "23" : "Claire",
    "24" : "Lechter",
    "25" : "Towa",
    "26" : "Patrick",
    "200" : "Jessica"
}